theboringlibrary/__init__.py
theboringlibrary/core.py
theboringlibrary-0.6.5.dist-info/LICENSE
theboringlibrary-0.6.5.dist-info/METADATA
theboringlibrary-0.6.5.dist-info/WHEEL
theboringlibrary-0.6.5.dist-info/entry_points.txt
theboringlibrary-0.6.5.dist-info/RECORD
